pyTBC/TraceBasedClustering.py
pyTBC/__init__.py
pyTBC-1.1.0.dist-info/LICENSE
pyTBC-1.1.0.dist-info/METADATA
pyTBC-1.1.0.dist-info/WHEEL
pyTBC-1.1.0.dist-info/top_level.txt
pyTBC-1.1.0.dist-info/RECORD
